SVNOnline
