Metadata-Version: 1.1
Name: SVNOnline
Version: 0.0.8
Summary: A svn online client.
Home-page: https://github.com/sintrb/SVNOnline
Author: sintrb
Author-email: sintrb@gmail.com
License: Apache
Keywords: svn,svn client,svn online
Platform: UNKNOWN
Classifier: Intended Audience :: Developers
Classifier: Operating System :: OS Independent
Classifier: Programming Language :: Python :: 2.7
